<annotation>
	<folder>Data0.9</folder>
	<filename>2019052031844_final.jpg</filename>
	<path>C:\IA\ocr-c\Data0.9\2019052031844_final.jpg</path>
	<source>
		<database>Unknown</database>
	</source>
	<size>
		<width>1200</width>
		<height>1600</height>
		<depth>1</depth>
	</size>
	<segmented>0</segmented>
	<object>
		<name>brand</name>
		<pose>Unspecified</pose>
		<truncated>0</truncated>
		<difficult>0</difficult>
		<bndbox>
			<xmin>386</xmin>
			<ymin>195</ymin>
			<xmax>839</xmax>
			<ymax>308</ymax>
		</bndbox>
	</object>
	<object>
		<name>payment</name>
		<pose>Unspecified</pose>
		<truncated>0</truncated>
		<difficult>0</difficult>
		<bndbox>
			<xmin>197</xmin>
			<ymin>690</ymin>
			<xmax>294</xmax>
			<ymax>723</ymax>
		</bndbox>
	</object>
	<object>
		<name>total</name>
		<pose>Unspecified</pose>
		<truncated>0</truncated>
		<difficult>0</difficult>
		<bndbox>
			<xmin>309</xmin>
			<ymin>646</ymin>
			<xmax>926</xmax>
			<ymax>695</ymax>
		</bndbox>
	</object>
	<object>
		<name>datetime</name>
		<pose>Unspecified</pose>
		<truncated>0</truncated>
		<difficult>0</difficult>
		<bndbox>
			<xmin>407</xmin>
			<ymin>1266</ymin>
			<xmax>706</xmax>
			<ymax>1313</ymax>
		</bndbox>
	</object>
	<object>
		<name>id</name>
		<pose>Unspecified</pose>
		<truncated>0</truncated>
		<difficult>0</difficult>
		<bndbox>
			<xmin>797</xmin>
			<ymin>1251</ymin>
			<xmax>922</xmax>
			<ymax>1301</ymax>
		</bndbox>
	</object>
</annotation>
