<annotation>
	<folder>Data0.9</folder>
	<filename>2019052734113_final.jpg</filename>
	<path>C:\IA\ocr-c\Data0.9\2019052734113_final.jpg</path>
	<source>
		<database>Unknown</database>
	</source>
	<size>
		<width>1200</width>
		<height>1600</height>
		<depth>1</depth>
	</size>
	<segmented>0</segmented>
	<object>
		<name>brand</name>
		<pose>Unspecified</pose>
		<truncated>0</truncated>
		<difficult>0</difficult>
		<bndbox>
			<xmin>271</xmin>
			<ymin>46</ymin>
			<xmax>957</xmax>
			<ymax>195</ymax>
		</bndbox>
	</object>
	<object>
		<name>total</name>
		<pose>Unspecified</pose>
		<truncated>0</truncated>
		<difficult>0</difficult>
		<bndbox>
			<xmin>232</xmin>
			<ymin>423</ymin>
			<xmax>952</xmax>
			<ymax>473</ymax>
		</bndbox>
	</object>
	<object>
		<name>payment</name>
		<pose>Unspecified</pose>
		<truncated>0</truncated>
		<difficult>0</difficult>
		<bndbox>
			<xmin>224</xmin>
			<ymin>515</ymin>
			<xmax>346</xmax>
			<ymax>548</ymax>
		</bndbox>
	</object>
	<object>
		<name>payment</name>
		<pose>Unspecified</pose>
		<truncated>0</truncated>
		<difficult>0</difficult>
		<bndbox>
			<xmin>742</xmin>
			<ymin>556</ymin>
			<xmax>929</xmax>
			<ymax>583</ymax>
		</bndbox>
	</object>
	<object>
		<name>total</name>
		<pose>Unspecified</pose>
		<truncated>0</truncated>
		<difficult>0</difficult>
		<bndbox>
			<xmin>209</xmin>
			<ymin>1243</ymin>
			<xmax>464</xmax>
			<ymax>1276</ymax>
		</bndbox>
	</object>
	<object>
		<name>id</name>
		<pose>Unspecified</pose>
		<truncated>0</truncated>
		<difficult>0</difficult>
		<bndbox>
			<xmin>227</xmin>
			<ymin>1078</ymin>
			<xmax>941</xmax>
			<ymax>1215</ymax>
		</bndbox>
	</object>
	<object>
		<name>id</name>
		<pose>Unspecified</pose>
		<truncated>0</truncated>
		<difficult>0</difficult>
		<bndbox>
			<xmin>792</xmin>
			<ymin>1231</ymin>
			<xmax>936</xmax>
			<ymax>1275</ymax>
		</bndbox>
	</object>
</annotation>
